{
  "title": "Hotel Chique interieur design",
  "slug": "hotel-chique-interieur-design",
  "excerpt": "Hotel chique interieurdesign omarmt een esthetiek van tijdloze elegantie en verfijning. Deze stijl is vaak te vinden in luxe boetiekhotels, resorts en high-end accommodaties. Het draait allemaal om he",
  "content": "Hotel chique interieurdesign omarmt een esthetiek van tijdloze elegantie en verfijning. Deze stijl is vaak te vinden in luxe boetiekhotels, resorts en high-end accommodaties. Het draait allemaal om het creëren van een gevoel van weelde en comfort voor gasten. In deze blog bespreken we de kenmerken van hotel chique interieur design. De Essentie van Hotel Chique interieur design Hotel chique interieurdesign creëert een wereld van weelde en comfort waarin gasten kunnen ontsnappen aan de dagelijkse drukte. Het is een combinatie van esthetiek, gastvrijheid en aandacht voor detail die een blijvende indruk achterlaat. Kleurenpalet Het kleurenpalet in hotel chique design is meestal neutraal en rustgevend. Denk aan zachte tinten zoals crème, beige, taupe en grijs. Deze kleuren creëren een kalmerende en uitnodigende sfeer in de hotelkamers en openbare ruimtes. Luxe Materialen Luxe materialen spelen een sleutelrol in het chique hotelinterieur. Materialen zoals marmer, fluweel, zijde, leer en gepolijst hout worden vaak gebruikt voor meubels, vloeren en accessoires. Deze materialen voegen een gevoel van weelde en rijkdom toe aan de ruimte. Elegant Meubilair Het meubilair in chique hotels is zorgvuldig geselecteerd en straalt elegantie uit. Denk aan klassieke meubelstukken met verfijnde lijnen en vormen. Comfortabele fauteuils, kingsize bedden met luxe beddengoed en chique eettafels dragen bij aan het gevoel van luxe. Verfijnde Verlichting Verlichting speelt een cruciale rol in het hotel chique interieurdesign. Kristallen kroonluchters, wandlampen met zachte tinten en subtiele accentverlichting creëren een warme en uitnodigende sfeer. Hiervoor werken we met merken als Penta Light en Occhio. Aandacht voor Comfort In chique hotels draait alles om het verwennen van de gasten. Zachte kussens, pluche tapijten en hoogwaardige matrassen zorgen voor een heerlijke nachtrust. Gasten worden omringd door luxe en comfort, wat bijdraagt aan een onvergetelijk verblijf.",
  "images": [
    "https://homeinspain.be/wp-content/uploads/2024/02/Hotel-Chic.jpg",
    "https://homeinspain.be/wp-content/uploads/2024/02/Hotel-Chic-1.jpg",
    "https://homeinspain.be/wp-content/uploads/2024/02/Hotel-Chic-2.jpg",
    "https://homeinspain.be/wp-content/uploads/2023/09/hotle-chique.jpeg",
    "https://homeinspain.be/wp-content/uploads/2024/02/Hotel-Chic-3.jpg",
    "https://homeinspain.be/wp-content/uploads/2024/02/Hotel-chic-4.jpg"
  ],
  "featuredImage": "https://homeinspain.be/wp-content/uploads/2024/02/Hotel-Chic-3.jpg"
}